Workbook
Name ASSUMPT: 'GROUP ASSIGNMENTS'!$A$3:$G$32

Sheet BUDGET
A3: Revenue | B3: August | C3: September | D3: October | E3: November | F3: December
A4: Wedding Invitations | B4: 4507 | C4: =B4*C27 -> 4731.8993 | D4: =C4*C27 -> 4968.0211 | E4: =D4*C27 -> 5215.9253 | F4: =E4*C27 -> 5476.2
A5: Birthday Party Invitations | B5: 3841 | C5: =B5*C28 -> 4207.8155 | D5: =C5*C28 -> 4609.6619 | E5: =D5*C28 -> 5049.8846 | F5: =E5*C28 -> 5532.1486
A6: Business Party Invitations | B6: 2652 | C6: =B6*C29 -> 2754.102 | D6: =C6*C29 -> 2860.1349 | E6: =D6*C29 -> 2970.2501 | F6: =E6*C29 -> 3084.6048
A7: Total Sales Revenue | B7: =SUM(B4:B6) -> 11000 | C7: =SUM(C4:C6) -> 11693.817 | D7: =SUM(D4:D6) -> 12437.818 | E7: =SUM(E4:E6) -> 13236.06 | F7: =SUM(F4:F6) -> 14092.953
A9: Expenses
A10: Printing Costs | B10: 4400 | C10: =C7*C34 -> 4677.5267 | D10: =D7*C34 -> 4975.1272 | E10: =E7*C34 -> 5294.424 | F10: =F7*C34 -> 5637.1813
A11: Salaries | B11: 3500 | C11: 3500 | D11: 3500 | E11: 3500 | F11: 3500
A12: Administration | B12: 550 | C12: =C7*C35 -> 584.69084 | D12: =D7*C35 -> 621.89089 | E12: =E7*C35 -> 661.803 | F12: =F7*C35 -> 704.64767
A13: Advertising | B13: 1544 | C13: =B13*C30 -> 1650.2272 | D13: =C13*C30 -> 1763.7628 | E13: =D13*C30 -> 1885.1097 | F13: =E13*C30 -> 2014.8053
A14: Legal Fees | B14: 788 | C14: =B14*C31 -> 804.3904 | D14: =C14*C31 -> 821.12172 | E14: =D14*C31 -> 838.20105 | F14: =E14*C31 -> 855.63563
A15: Shipping | B15: 928 | C15: =B15*C32 -> 965.2128 | D15: =C15*C32 -> 1003.9178 | E15: =D15*C32 -> 1044.1749 | F15: =E15*C32 -> 1086.0464
A16: Total Expenses | B16: =SUM(B10:B15) -> 11710 | C16: =SUM(C10:C15) -> 12182.048 | D16: =SUM(D10:D15) -> 12685.82 | E16: =SUM(E10:E15) -> 13223.713 | F16: =SUM(F10:F15) -> 13798.316
A18: Net Income before Taxes | B18: =B7-B16 -> -710 | C18: =C7-C16 -> -488.23116 | D18: =D7-D16 -> -248.00255 | E18: =E7-E16 -> 12.347316 | F18: =F7-F16 -> 294.63708
A19: Taxes | B19: 0 | C19: 0 | D19: 0 | E19: 3.4572486 | F19: 82.498381
A20: Net Profit (loss) | B20: -710 | C20: =C18-C19 -> -488.23116 | D20: =D18-D19 -> -248.00255 | E20: =E18-E19 -> 8.8900678 | F20: =F18-F19 -> 212.13869
A26: Projected Growth Per Month | B26: % | C26: Actual Values
A27: Wedding Invitations | B27: =VLOOKUP(22,'GROUP ASSIGNMENTS'!A1:H37,2,FALSE) -> 4.99 | C27: 1.0499
A28: Birthday Party Invitations | B28: =VLOOKUP(22,'GROUP ASSIGNMENTS'!A1:H37,3,FALSE) -> 9.55 | C28: 1.0955
A29: Business Party Invitations | B29: =VLOOKUP(22,'GROUP ASSIGNMENTS'!A1:H37,4,FALSE) -> 3.85 | C29: 1.0385
A30: Advertising | B30: =VLOOKUP(22,'GROUP ASSIGNMENTS'!A1:H37,5,FALSE) -> 6.88 | C30: 1.0688
A31: Legal Fees | B31: =VLOOKUP(22,'GROUP ASSIGNMENTS'!A1:H37,6,FALSE) -> 2.08 | C31: 1.0208
A32: Shipping | B32: =VLOOKUP(22,'GROUP ASSIGNMENTS'!A1:H37,7,FALSE) -> 4.01 | C32: 1.0401
A33: December Increase Goal | B33: =VLOOKUP(22,'GROUP ASSIGNMENTS'!A1:H37,8,FALSE) -> 20.86 | C33: 1.2086
A34: Printing Costs | B34: 40 | C34: 0.4
A35: Administration | B35: 5 | C35: 0.05

Sheet TREND CHART

Sheet DISTRIBUTION

Sheet SOLVER
A3: Revenue | B3: August | C3: September | D3: October | E3: November | F3: December
A4: Wedding Invitations | B4: 4507 | C4: =B4*C27 -> 4731.8993 | D4: =C4*C27 -> 4968.0211 | E4: =D4*C27 -> 5215.9253 | F4: =E4*C27 -> 5476.2
A5: Birthday Party Invitations | B5: 3841 | C5: =B5*C28 -> 4207.8155 | D5: =C5*C28 -> 4609.6619 | E5: =D5*C28 -> 5049.8846 | F5: =E5*C28 -> 5532.1486
A6: Business Party Invitations | B6: 2652 | C6: =B6*C29 -> 2754.102 | D6: =C6*C29 -> 2860.1349 | E6: =D6*C29 -> 2970.2501 | F6: =E6*C29 -> 3084.6048
A7: Total Sales Revenue | B7: =SUM(B4:B6) -> 11000 | C7: =SUM(C4:C6) -> 11693.817 | D7: =SUM(D4:D6) -> 12437.818 | E7: =SUM(E4:E6) -> 13236.06 | F7: =SUM(F4:F6) -> 14092.953
A9: Expenses
A10: Printing Costs | B10: 4400 | C10: =C7*C34 -> 4677.5267 | D10: =D7*C34 -> 4975.1272 | E10: =E7*C34 -> 5294.424 | F10: =F7*C34 -> 5637.1813
A11: Salaries | B11: 3500 | C11: 3500 | D11: 3500 | E11: 3500 | F11: 3500
A12: Administration | B12: 550 | C12: =C7*C35 -> 584.69084 | D12: =D7*C35 -> 621.89089 | E12: =E7*C35 -> 661.803 | F12: =F7*C35 -> 704.64767
A13: Advertising | B13: 1544 | C13: =B13*C30 -> 1650.2272 | D13: =C13*C30 -> 1763.7628 | E13: =D13*C30 -> 1885.1097 | F13: =E13*C30 -> 2014.8053
A14: Legal Fees | B14: 788 | C14: =B14*C31 -> 804.3904 | D14: =C14*C31 -> 821.12172 | E14: =D14*C31 -> 838.20105 | F14: =E14*C31 -> 855.63563
A15: Shipping | B15: 928 | C15: =B15*C32 -> 965.2128 | D15: =C15*C32 -> 1003.9178 | E15: =D15*C32 -> 1044.1749 | F15: =E15*C32 -> 1086.0464
A16: Total Expenses | B16: =SUM(B10:B15) -> 11710 | C16: =SUM(C10:C15) -> 12182.048 | D16: =SUM(D10:D15) -> 12685.82 | E16: =SUM(E10:E15) -> 13223.713 | F16: =SUM(F10:F15) -> 13798.316
A18: Net Income before Taxes | B18: =B7-B16 -> -710 | C18: =C7-C16 -> -488.23116 | D18: =D7-D16 -> -248.00255 | E18: =E7-E16 -> 12.347316 | F18: =F7-F16 -> 294.63708
A19: Taxes | B19: 0 | C19: 0 | D19: 0 | E19: 3.4572486 | F19: 82.498381
A20: Net Profit (loss) | B20: -710 | C20: =C18-C19 -> -488.23116 | D20: =D18-D19 -> -248.00255 | E20: =E18-E19 -> 8.8900678 | F20: =F18-F19 -> 212.13869
A26: Manipulated Projected Growth Per Month | B26: % | C26: Actual Values
A27: Wedding Invitations | B27: 0.050331738 | C27: 1.0499
A28: Birthday Party Invitations | B28: 0.097031005 | C28: 1.0955
A29: Business Party Invitations | B29: 0.038646353 | C29: 1.0385
A30: Advertising | B30: 0.068503379 | C30: 1.0688 | D30: SOLVER
A31: Legal Fees | B31: 0.020787945 | C31: 1.0208 | D31: GOAL
A32: Shipping | B32: 0.040044185 | C32: 1.0401
A33: December Increase Goal | B33: 0.2086 | C33: 1.2086 | D33: =F20*C33 -> 256.39083
A34: Printing Costs | B34: 0.4 | C34: 0.4
A35: Administration | B35: 0.05 | C35: 0.05

Sheet SALES
A1: Order Date | B1: Region | C1: Representative | D1: Invitation type | E1: Units (100) | F1: Unit Cost | G1: Total
A2: 43836 | B2: East | C2: Jones | D2: Birthday | E2: 95 | F2: 1.99 | G2: =E2*100*F2 -> 18905
A3: 43853 | B3: Central | C3: Kivell | D3: Business | E3: 50 | F3: 3.49 | G3: =E3*100*F3 -> 17450
A4: 43870 | B4: Central | C4: Jardine | D4: Birthday | E4: 36 | F4: 4.99 | G4: =E4*100*F4 -> 17964
A5: 43887 | B5: Central | C5: Gill | D5: Wedding | E5: 27 | F5: 1.99 | G5: =E5*100*F5 -> 5373
A6: 43905 | B6: West | C6: Sorvino | D6: Birthday | E6: 56 | F6: 2.99 | G6: =E6*100*F6 -> 16744
A7: 43922 | B7: East | C7: Jones | D7: Business | E7: 60 | F7: 4.99 | G7: =E7*100*F7 -> 29940
A8: 43939 | B8: Central | C8: Andrews | D8: Birthday | E8: 75 | F8: 1.99 | G8: =E8*100*F8 -> 14925
A9: 43956 | B9: Central | C9: Jardine | D9: Birthday | E9: 90 | F9: 4.99 | G9: =E9*100*F9 -> 44910
A10: 43973 | B10: West | C10: Thompson | D10: Birthday | E10: 32 | F10: 1.99 | G10: =E10*100*F10 -> 6368
A11: 43990 | B11: East | C11: Jones | D11: Business | E11: 60 | F11: 0.85 | G11: =E11*100*F11 -> 5100
A12: 44007 | B12: Central | C12: Morgan | D12: Birthday | E12: 90 | F12: 4.99 | G12: =E12*100*F12 -> 44910
A13: 44024 | B13: East | C13: Howard | D13: Business | E13: 29 | F13: 1.99 | G13: =E13*100*F13 -> 5771
... A44: 44551 | B44: Central | C44: Andrews | D44: Business | E44: 28 | F44: 1.21 | G44: =E44*100*F44 -> 3388

Sheet PIVOT TABLE
B4: Column Labels
B5: Birthday | D5: Business | F5: Graduation | H5: Wedding | J5: Total Sum of Total | K5: Total Count of Units (100)
A6: Row Labels | B6: Sum of Total | C6: Count of Units (100) | D6: Sum of Total | E6: Count of Units (100) | F6: Sum of Total | G6: Count of Units (100) | H6: Sum of Total | I6: Count of Units (100)
A7: Andrews | B7: 29865 | C7: 3 | D7: 3388 | E7: 1 | J7: 33253 | K7: 4
A8: 2020 | B8: 14925 | C8: 1 | J8: 14925 | K8: 1
A9: 2021 | B9: 14940 | C9: 2 | D9: 3388 | E9: 1 | J9: 18328 | K9: 3
A10: Gill | B10: 7740 | C10: 2 | D10: 49674 | E10: 2 | H10: 5373 | I10: 1 | J10: 62787 | K10: 5
A11: 2020 | H11: 5373 | I11: 1 | J11: 5373 | K11: 1
A12: 2021 | B12: 7740 | C12: 2 | D12: 49674 | E12: 2 | J12: 57414 | K12: 4
A13: Howard | D13: 5771 | E13: 1 | H13: 47904 | I13: 1 | J13: 53675 | K13: 2
A14: 2020 | D14: 5771 | E14: 1 | J14: 5771 | K14: 1
A15: 2021 | H15: 47904 | I15: 1 | J15: 47904 | K15: 1
A16: Jardine | B16: 62874 | C16: 2 | D16: 19344 | E16: 2 | F16: 24950 | G16: 1 | J16: 107168 | K16: 5
A17: 2020 | B17: 62874 | C17: 2 | J17: 62874 | K17: 2
A18: 2021 | D18: 19344 | E18: 2 | F18: 24950 | G18: 1 | J18: 44294 | K18: 3
A19: Jones | B19: 26850 | C19: 2 | D19: 37036 | E19: 3 | F19: 14106 | G19: 2 | H19: 8640 | I19: 1 | J19: 86632 | K19: 8
A20: 2020 | B20: 26850 | C20: 2 | D20: 35040 | E20: 2 | F20: 2512 | G20: 1 | H20: 8640 | I20: 1 | J20: 73042 | K20: 6
A21: 2021 | D21: 1996 | E21: 1 | F21: 11594 | G21: 1 | J21: 13590 | K21: 2
A22: Kivell | D22: 17450 | E22: 1 | F22: 31344 | G22: 2 | H22: 750 | I22: 1 | J22: 49544 | K22: 4
A23: 2020 | D23: 17450 | E23: 1 | F23: 22272 | G23: 1 | J23: 39722 | K23: 2
A24: 2021 | F24: 9072 | G24: 1 | H24: 750 | I24: 1 | J24: 9822 | K24: 2
A25: Morgan | B25: 44910 | C25: 1 | D25: 8792 | E25: 1 | F25: 13695 | G25: 1 | J25: 67397 | K25: 3
A26: 2020 | B26: 44910 | C26: 1 | D26: 8792 | E26: 1 | J26: 53702 | K26: 2
A27: 2021 | F27: 13695 | G27: 1 | J27: 13695 | K27: 1
A28: Parent | D28: 9234 | E28: 1 | F28: 23458 | G28: 1 | H28: 1455 | I28: 1 | J28: 34147 | K28: 3
A29: 2020 | D29: 9234 | E29: 1 | F29: 23458 | G29: 1 | H29: 1455 | I29: 1 | J29: 34147 | K29: 3
A30: Smith | B30: 8643 | C30: 1 | D30: 130500 | E30: 1 | H30: 500 | I30: 1 | J30: 139643 | K30: 3
A31: 2020 | B31: 8643 | C31: 1 | H31: 500 | I31: 1 | J31: 9143 | K31: 2
A32: 2021 | D32: 130500 | E32: 1 | J32: 130500 | K32: 1
A33: Sorvino | B33: 16744 | C33: 1 | D33: 13993 | E33: 1 | H33: 15868 | I33: 2 | J33: 46605 | K33: 4
A34: 2020 | B34: 16744 | C34: 1 | J34: 16744 | K34: 1
A35: 2021 | D35: 13993 | E35: 1 | H35: 15868 | I35: 2 | J35: 29861 | K35: 3
A36: Thompson | B36: 6368 | C36: 1 | D36: 9804 | E36: 1 | J36: 16172 | K36: 2
A37: 2020 | B37: 6368 | C37: 1 | J37: 6368 | K37: 1
A38: 2021 | D38: 9804 | E38: 1 | J38: 9804 | K38: 1
A39: Grand Total | B39: 203994 | C39: 13 | D39: 304986 | E39: 15 | F39: 107553 | G39: 7 | H39: 80490 | I39: 8 | J39: 697023 | K39: 43

Sheet GROUP ASSIGNMENTS
A1: Group | B1: Wedding Invitations | C1: Birthday Party Invitations | D1: Business Party Invitations | E1: Advertising | F1: Legal Fees | G1: Shipping | H1: Deceember Goal Increase
A2: # | B2: A | C2: B | D2: C | E2: D | F2: E | G2: F | H2: G
A3: 1 | B3: 4.22 | C3: 9.22 | D3: 3.47 | E3: 5.54 | F3: 4.09 | G3: 4.17 | H3: 20.08
A4: 2 | B4: 3.74 | C4: 8.22 | D4: 5.89 | E4: 4.2 | F4: 3.68 | G4: 6.66 | H4: 19.93
A5: 3 | B5: 4.17 | C5: 9.37 | D5: 4.21 | E5: 6.74 | F5: 3.62 | G5: 6.66 | H5: 20.92
A6: 4 | B6: 4.77 | C6: 8.44 | D6: 3.85 | E6: 5.47 | F6: 2.8 | G6: 6.66 | H6: 18.47
A7: 5 | B7: 5.24 | C7: 7.88 | D7: 5.89 | E7: 5.89 | F7: 3.44 | G7: 4.22 | H7: 19.12
A8: 6 | B8: 3.55 | C8: 8.33 | D8: 4.75 | E8: 5.92 | F8: 2.81 | G8: 5.21 | H8: 18.92
A9: 7 | B9: 4.56 | C9: 8.21 | D9: 3.69 | E9: 5.47 | F9: 3.44 | G9: 4.5 | H9: 19.53
A10: 8 | B10: 5.73 | C10: 8.65 | D10: 4.37 | E10: 4.29 | F10: 3.98 | G10: 5.34 | H10: 19.21
A11: 9 | B11: 5.83 | C11: 8.44 | D11: 4.77 | E11: 5.89 | F11: 3.12 | G11: 5.8 | H11: 20.16
A12: 10 | B12: 4.3 | C12: 9.38 | D12: 4.56 | E12: 6.47 | F12: 3.45 | G12: 5.34 | H12: 19.54
A13: 11 | B13: 4.22 | C13: 8.21 | D13: 4.56 | E13: 4.99 | F13: 3.21 | G13: 4.01 | H13: 20.42
A14: 12 | B14: 5.24 | C14: 7.92 | D14: 5.55 | E14: 5.68 | F14: 4.64 | G14: 5.26 | H14: 18.34
... A37: 35 | B37: 5.6 | C37: 7.53 | D37: 5.63 | E37: 4.76 | F37: 3.06 | G37: 4.22 | H37: 19.67
